cv2_collage_v2/LICENSE
cv2_collage_v2/README.md
cv2_collage_v2/__init__.py
cv2_collage_v2/requirements.txt
cv2_collage_v2/thirdparty.json
cv2_collage_v2-0.11.dist-info/LICENSE.rst
cv2_collage_v2-0.11.dist-info/METADATA
cv2_collage_v2-0.11.dist-info/WHEEL
cv2_collage_v2-0.11.dist-info/top_level.txt
cv2_collage_v2-0.11.dist-info/RECORD
