Metadata-Version: 2.1
Name: cv2-collage-v2
Version: 0.11
Summary: Creates a collage from images with OpenCV
Home-page: https://github.com/hansalemaos/cv2_collage_v2
Author: Johannes Fischer
Author-email: aulasparticularesdealemaosp@gmail.com
License: MIT
Keywords: collage,opencv
Classifier: Development Status :: 4 - Beta
Classifier: Programming Language :: Python :: 3 :: Only
Classifier: Programming Language :: Python :: 3.10
Classifier: Topic :: Software Development :: Libraries :: Python Modules
Classifier: Topic :: Utilities
License-File: LICENSE.rst
Requires-Dist: a-cv2-easy-resize
Requires-Dist: a-cv-imwrite-imread-plus
Requires-Dist: create-empty-image
Requires-Dist: numpy
Requires-Dist: opencv-python
Requires-Dist: rectangle-packer
